README.rst
setup.py
PyDataColl.egg-info/PKG-INFO
PyDataColl.egg-info/SOURCES.txt
PyDataColl.egg-info/dependency_links.txt
PyDataColl.egg-info/entry_points.txt
PyDataColl.egg-info/requires.txt
PyDataColl.egg-info/top_level.txt
pydatacoll/__init__.py
pydatacoll/api_server.py
pydatacoll/plugins/__init__.py
pydatacoll/plugins/db_save.py
pydatacoll/plugins/device_manage.py
pydatacoll/plugins/formula_calc.py
pydatacoll/protocols/__init__.py
pydatacoll/protocols/formula/__init__.py
pydatacoll/protocols/formula/device.py
pydatacoll/protocols/iec104/__init__.py
pydatacoll/protocols/iec104/device.py
pydatacoll/protocols/iec104/frame.py
pydatacoll/resources/__init__.py
pydatacoll/resources/protocol.py
pydatacoll/resources/redis_key.py
pydatacoll/utils/__init__.py
pydatacoll/utils/func_container.py
pydatacoll/utils/json_response.py
pydatacoll/utils/logger.py
pydatacoll/utils/read_config.py
pydatacoll/utils/asteval/__init__.py
pydatacoll/utils/asteval/asteval.py
pydatacoll/utils/asteval/astutils.py
test/__init__.py
test/device_test.py
test/load_test.py
test/test_db_save_plugin.py
test/test_formula_calc.py
test/test_iec104_device.py
test/test_iec104_frame.py
test/test_interface.py
test/test_load.py
test/test_utils.py
test/mock_device/__init__.py
test/mock_device/iec104device.py
test/mock_device/mock_data.py