Metadata-Version: 1.1
Name: PyDataColl
Version: 0.1
Summary: PyDataColl is a SCADA-like system, originally developed at GDT.
Home-page: http://pydatacoll.readthedocs.org/
Author: timercrack
Author-email: timercrack@gmail.com
License: http://www.apache.org/licenses/LICENSE-2.0
Keywords: IEC60870 SCADA EMS
Platform: UNKNOWN
Classifier: Environment :: Console
Classifier: Intended Audience :: Information Technology
Classifier: License :: OSI Approved :: Apache Software License
Classifier: Programming Language :: Python :: 3.5
Classifier: Programming Language :: Python :: Implementation :: CPython
Classifier: Intended Audience :: Information Technology
Classifier: Natural Language :: English
Classifier: Natural Language :: Chinese (Simplified)
Classifier: Operating System :: Microsoft :: Windows
Classifier: Operating System :: POSIX
Classifier: Operating System :: MacOS
Classifier: Topic :: Scientific/Engineering
Classifier: Topic :: Scientific/Engineering :: Interface Engine/Protocol Translator
